[
  {
    "Username": "GanesGanteng",
    "PasswordHash": "OTfdgSaeD0TZmDgfCx\u002BDT1prT9V7nVZOTcvG7/8rwd8="
  },
  {
    "Username": "GanesGanteng",
    "PasswordHash": "1RKOroXDY6GA9P00waSTIiMUhoEcZ7dVL1A2bhF8ILE="
  },
  {
    "Username": "GanesGanteng",
    "PasswordHash": "9RJTAdusFl8bjDZtP19HIpEJePHTIyozFvtPmIh\u002Br4k="
  },
  {
    "Username": "GanesGanteng",
    "PasswordHash": "HOolUH1mIQl3G2gA7IMG2dD2kGmeDoNUllhlEdeQXGs="
  },
  {
    "Username": "GanesGanteng",
    "PasswordHash": "jFibNlCkdW3SwN9Kj\u002Bg\u002BgGmY/XhqClrn5PmShVZg864="
  }
]